SKTransformer/SKTransformer.py
SKTransformer/__init__.py
SKTransformer/call.py
SKTransformer/matrix.py
SKTransformer/tuning.py
SKTransformer-1.1.dist-info/METADATA
SKTransformer-1.1.dist-info/WHEEL
SKTransformer-1.1.dist-info/top_level.txt
SKTransformer-1.1.dist-info/RECORD
