Metadata-Version: 2.1
Name: SKTransformer
Version: 1.1
Summary: UNKNOWN
Home-page: https://github.com/Kowsher/SKTransformer
Author: Kowsher
Author-email: ahmedshuvo969@gmail.com
License: MIT
Platform: UNKNOWN
Classifier: Programming Language :: Python :: 3
Classifier: License :: OSI Approved :: MIT License
Classifier: Operating System :: OS Independent
Requires-Dist: transformers
Requires-Dist: torch
Requires-Dist: numpy
Requires-Dist: typing
Requires-Dist: call
Requires-Dist: scikit-learn
